[1,0,0,[["cc.AnimationClip",["_name","_duration","sample","wrapMode","curveData"],-2]],[[0,0,1,2,3,4,6]],[[0,"LightOnTop",2,25,2,{"paths":{"gfs_vfx_c_screen":{"props":{"angle":[{"frame":0,"value":0},{"frame":1,"value":41.999998},{"frame":2,"value":0}]}},"sd_vfx_a_screen_01":{"props":{"angle":[{"frame":0,"value":0},{"frame":1,"value":-41.999998},{"frame":2,"value":0}]}},"main_ambient_vfx_b_screen_02":{"props":{"angle":[{"frame":0,"value":15},{"frame":1.2,"value":-15},{"frame":2,"value":15}]}},"main_ambient_vfx_b_screen_03":{"props":{"angle":[{"frame":0,"value":-15},{"frame":1,"value":15},{"frame":2,"value":-15}]}},"main_ambient_vfx_b_screen_02_Left":{"props":{"angle":[{"frame":0,"value":5},{"frame":0.64,"value":-20},{"frame":2,"value":5}]}},"main_ambient_vfx_b_screen_04_right":{"props":{"angle":[{"frame":0,"value":-5},{"frame":0.64,"value":20},{"frame":2,"value":-5}]}}}}]],0,0,[],[],[]]